[
  {
    "title": "Agentic AI Solutions",
    "img": "/light/assets/imgs/serv-icons/3.png",
    "desc": "Production-grade agentic AI agents trained on your business for sales, support, operations, and knowledge work. Deployed in 4-8 weeks for Singapore SMEs.",
    "link": "/solutions/agentic-ai"
  },
  {
    "title": "AI-Native Web & App",
    "img": "/light/assets/imgs/serv-icons/4.png",
    "desc": "AI-native websites and apps engineered to convert, with automation and data hooks built in from day one.",
    "link": "/solutions/web-app"
  },
  {
    "title": "Digital Growth Services",
    "img": "/light/assets/imgs/serv-icons/5.png",
    "desc": "Content, performance creative, and SEO systems that bring qualified demand into the workflows your agents convert.",
    "link": "/solutions/digital-growth"
  }
]
